torchTrainify/__init__.py
torchTrainify/classTrainer.py
torchTrainify-0.1.3.dist-info/LICENSE.txt
torchTrainify-0.1.3.dist-info/METADATA
torchTrainify-0.1.3.dist-info/WHEEL
torchTrainify-0.1.3.dist-info/top_level.txt
torchTrainify-0.1.3.dist-info/RECORD
